LICENSE
MANIFEST.in
README.md
requirements.txt
setup.py
yuma/__init__.py
yuma/model.py
yuma/permission.py
yuma.egg-info/PKG-INFO
yuma.egg-info/SOURCES.txt
yuma.egg-info/dependency_links.txt
yuma.egg-info/not-zip-safe
yuma.egg-info/requires.txt
yuma.egg-info/top_level.txt
yuma/mysql/__init__.py
yuma/mysql/build.py